LICENSE
MANIFEST.in
README.md
setup.cfg
setup.py
tilejet_cache.egg-info/PKG-INFO
tilejet_cache.egg-info/SOURCES.txt
tilejet_cache.egg-info/dependency_links.txt
tilejet_cache.egg-info/top_level.txt
tilejetcache/__init__.py
tilejetcache/cache.py