Metadata-Version: 1.1
Name: tilejet-cache
Version: 0.0.3
Summary: A performant python library for caching tiles in-memory using memcached.
Home-page: https://github.com/tilejet/tilejet-cache/
Author: TileJet Developers
Author-email: tilejet.dev@gmail.com
License: MIT License
Download-URL: https://github.com/tilejet/tilejet-cache/zipball/master
Keywords: python gis tilejet
Platform: UNKNOWN
Classifier: Development Status :: 4 - Beta
Classifier: Intended Audience :: Developers
Classifier: License :: OSI Approved :: MIT License
Classifier: Topic :: Software Development :: Libraries :: Python Modules
